uw_course/__init__.py
uw_course/main.py
uw_course/setting.py
uw_course/ClassSchedule/SearchInfo.py
uw_course/ClassSchedule/__init__.py
uw_course/ClassSchedule/runner.py
uw_course/DB/__init__.py
uw_course/DB/dbClass.py
uw_course/Utiles/__init__.py
uw_course/Utiles/colorMessage.py
uw_course/Utiles/manageDBClass.py
uw_course/Utiles/randomColor.py
uw_course-1.0.2.dist-info/LICENSE
uw_course-1.0.2.dist-info/METADATA
uw_course-1.0.2.dist-info/WHEEL
uw_course-1.0.2.dist-info/entry_points.txt
uw_course-1.0.2.dist-info/top_level.txt
uw_course-1.0.2.dist-info/RECORD
