Metadata-Version: 2.1
Name: uw-course
Version: 1.0.2
Summary: A course helper tool for managing UW courses schedule
Author-email: Jiucheng Zang <zangjiucheng@gmail.com>
License: MIT
Project-URL: homepage, https://github.com/zangjiucheng/CourseExplorer
Project-URL: repository, https://github.com/zangjiucheng/CourseExplorer
Requires-Python: >=3.7
License-File: LICENSE
Requires-Dist: attrs
Requires-Dist: certifi
Requires-Dist: click
Requires-Dist: dnspython
Requires-Dist: pdfschedule
Requires-Dist: Pillow
Requires-Dist: pymongo
Requires-Dist: PyYAML
Requires-Dist: reportlab
